trame_monitor/__init__.py
trame_monitor/app/__init__.py
trame_monitor/app/jupyter.py
trame_monitor/app/main.py
trame_monitor/app/engine/__init__.py
trame_monitor/app/engine/executor.py
trame_monitor/app/engine/resource.py
trame_monitor/app/ui/__init__.py
trame_monitor/app/ui/cpu.py
trame_monitor/app/ui/launcher.py
trame_monitor/app/ui/memory.py
trame_monitor/examples/__init__.py
trame_monitor/examples/cone.py
trame_monitor/examples/sphere.py
trame_monitor-1.0.0.dist-info/LICENSE
trame_monitor-1.0.0.dist-info/METADATA
trame_monitor-1.0.0.dist-info/WHEEL
trame_monitor-1.0.0.dist-info/entry_points.txt
trame_monitor-1.0.0.dist-info/top_level.txt
trame_monitor-1.0.0.dist-info/RECORD
