Metadata-Version: 2.1
Name: trame-monitor
Version: 1.0.0
Summary: Server resource monitoring
Home-page: UNKNOWN
Author: Kitware Inc.
License: Apache Software License
Keywords: Python,Interactive,Web,Application,Framework
Platform: UNKNOWN
Classifier: Development Status :: 4 - Beta
Classifier: Environment :: Web Environment
Classifier: License :: OSI Approved :: Apache Software License
Classifier: Natural Language :: English
Classifier: Operating System :: OS Independent
Classifier: Programming Language :: Python :: 3 :: Only
Classifier: Programming Language :: JavaScript
Classifier: Topic :: Software Development :: Libraries :: Application Frameworks
Classifier: Topic :: Software Development :: Libraries :: Python Modules
License-File: LICENSE
Requires-Dist: trame (>=2.0.0rc2)
Requires-Dist: psutil
Requires-Dist: pyyaml
